{"HealthStart":0.0,"HealthStop":0.0,"StrengthStart":1.0,"StrengthStop":1.0,"LockDoorChanceStart":0.800000011920929,"LockDoorChanceStop":1.0,"BarricadeDoorChanceStart":0.800000011920929,"BarricadeDoorChanceStop":1.0,"HideChanceStart":0.8999999761581421,"HideChanceStop":0.8999999761581421,"ShotDetectionStart":0.5,"ShotDetectionStop":1.0,"FirstDecisionTimeStart":15.0,"FirstDecisionTimeStop":20.0,"ShooterLocationDistanceStart":15.0,"ShooterLocationDistanceStop":15.0,"ForceDoorOpenStart":0.10000000149011612,"ForceDoorOpenStop":0.0,"AltruismStart":0.0,"AltruismStop":0.0,"horizontalDeviation":3.0,"verticalUpDeviation":2.0,"verticalDownDeviation":1.5,"firingRate":1.5,"ShootStrength":5.0,"aboveMeWeight":1.0,"distanceWeight":0.20000000298023225,"notAboveMeWeight":1.0,"altruismWeight":0.0,"floorWeight":0.5,"familiarityWeight":0.30000001192092898,"shooterCheckRoomWeight":0.10000000149011612,"shooterSearchFloor":0.800000011920929,"shooterGoUp":0.20000000298023225,"shooterGoDown":0.20000000298023225,"victimStairsWeight":0.699999988079071,"LawEnforcementArrival":15.0,"BarricadingTime":240.0,"FiringRateSpeedUpEnabled":true,"SimulationsCount":10,"basicEvacuationChanceStart":0.800000011920929,"basicEvacuationChanceStop":1.0,"basicHideChanceStart":0.0,"basicHideChanceStop":0.20000000298023225,"basicFightChanceStart":0.30000001192092898,"basicFightChanceStop":0.699999988079071,"myRoomChanceStart":0.0,"myRoomChanceStop":0.0,"anyRoomChanceStart":0.0,"anyRoomChanceStop":0.0,"exitChanceStart":0.0,"exitChanceStop":0.0,"DropGunProbability":10.0,"ShootProbability":90.0,"freezeStart":1.0,"freezeStop":2.0,"freezeChanceStart":0.4000000059604645,"freezeChanceStop":0.6000000238418579}
