{"SimulationId":1,"DeathTime":26.481834411621095,"BehaviourName":"ImplementedBehaviours+Work","ActionName":"WorkActions+GoToWork","Floor":0,"InRoom":true}
{"SimulationId":1,"DeathTime":39.481834411621097,"BehaviourName":"ImplementedBehaviours+Fight","ActionName":"FightActions+Fight","Floor":0,"InRoom":true}
{"SimulationId":1,"DeathTime":51.3818359375,"BehaviourName":"ImplementedBehaviours+Fight","ActionName":"FightActions+Fight","Floor":0,"InRoom":false}
{"SimulationId":1,"DeathTime":66.3818359375,"BehaviourName":"ImplementedBehaviours+Evacuate","ActionName":"EvacuationActions+RunAway","Floor":0,"InRoom":false}
{"SimulationId":1,"DeathTime":66.3818359375,"BehaviourName":"ImplementedBehaviours+Fight","ActionName":"FightActions+Fight","Floor":0,"InRoom":false}
{"SimulationId":1,"DeathTime":69.3818359375,"BehaviourName":"ImplementedBehaviours+Fight","ActionName":"FightActions+Fight","Floor":0,"InRoom":false}
{"SimulationId":1,"DeathTime":69.3818359375,"BehaviourName":"ImplementedBehaviours+Fight","ActionName":"FightActions+Fight","Floor":0,"InRoom":false}
{"SimulationId":1,"DeathTime":72.3818359375,"BehaviourName":"ImplementedBehaviours+Fight","ActionName":"FightActions+Fight","Floor":0,"InRoom":false}
{"SimulationId":1,"DeathTime":72.3818359375,"BehaviourName":"ImplementedBehaviours+Fight","ActionName":"FightActions+Fight","Floor":0,"InRoom":false}
{"SimulationId":1,"DeathTime":72.3818359375,"BehaviourName":"ImplementedBehaviours+Evacuate","ActionName":"EvacuationActions+RunToExit","Floor":0,"InRoom":false}
{"SimulationId":1,"DeathTime":72.3818359375,"BehaviourName":"ImplementedBehaviours+Fight","ActionName":"FightActions+Fight","Floor":0,"InRoom":false}
{"SimulationId":1,"DeathTime":75.3818359375,"BehaviourName":"ImplementedBehaviours+Fight","ActionName":"FightActions+Fight","Floor":0,"InRoom":false}
{"SimulationId":1,"DeathTime":75.3818359375,"BehaviourName":"ImplementedBehaviours+Evacuate","ActionName":"EvacuationActions+RunToExit","Floor":0,"InRoom":false}
{"SimulationId":1,"DeathTime":75.3818359375,"BehaviourName":"ImplementedBehaviours+Evacuate","ActionName":"EvacuationActions+RunToExit","Floor":0,"InRoom":false}
{"SimulationId":1,"DeathTime":78.3818359375,"BehaviourName":"ImplementedBehaviours+Fight","ActionName":"FightActions+Fight","Floor":0,"InRoom":false}
{"SimulationId":1,"DeathTime":78.3818359375,"BehaviourName":"ImplementedBehaviours+Evacuate","ActionName":"EvacuationActions+RunToExit","Floor":0,"InRoom":false}
{"SimulationId":1,"DeathTime":78.3818359375,"BehaviourName":"ImplementedBehaviours+Evacuate","ActionName":"EvacuationActions+RunToExit","Floor":0,"InRoom":false}
{"SimulationId":1,"DeathTime":78.3818359375,"BehaviourName":"ImplementedBehaviours+Evacuate","ActionName":"EvacuationActions+RunToExit","Floor":0,"InRoom":false}
{"SimulationId":1,"DeathTime":81.3818359375,"BehaviourName":"ImplementedBehaviours+Fight","ActionName":"FightActions+Fight","Floor":0,"InRoom":false}
{"SimulationId":1,"DeathTime":81.3818359375,"BehaviourName":"ImplementedBehaviours+Evacuate","ActionName":"EvacuationActions+RunToExit","Floor":0,"InRoom":false}
{"SimulationId":1,"DeathTime":81.3818359375,"BehaviourName":"ImplementedBehaviours+Evacuate","ActionName":"EvacuationActions+RunAway","Floor":0,"InRoom":false}
{"SimulationId":1,"DeathTime":87.3818359375,"BehaviourName":"ImplementedBehaviours+Evacuate","ActionName":"EvacuationActions+RunToExit","Floor":0,"InRoom":false}
{"SimulationId":1,"DeathTime":87.3818359375,"BehaviourName":"ImplementedBehaviours+Fight","ActionName":"FightActions+Fight","Floor":0,"InRoom":false}
{"SimulationId":1,"DeathTime":90.3818359375,"BehaviourName":"ImplementedBehaviours+Fight","ActionName":"FightActions+Fight","Floor":0,"InRoom":false}
{"SimulationId":1,"DeathTime":90.3818359375,"BehaviourName":"ImplementedBehaviours+Fight","ActionName":"FightActions+Fight","Floor":0,"InRoom":false}
{"SimulationId":1,"DeathTime":93.3818359375,"BehaviourName":"ImplementedBehaviours+Evacuate","ActionName":"EvacuationActions+RunToMyRoom","Floor":0,"InRoom":false}
{"SimulationId":1,"DeathTime":96.3818359375,"BehaviourName":"ImplementedBehaviours+Evacuate","ActionName":"EvacuationActions+RunToExit","Floor":0,"InRoom":false}
{"SimulationId":1,"DeathTime":96.3818359375,"BehaviourName":"ImplementedBehaviours+Fight","ActionName":"FightActions+Fight","Floor":0,"InRoom":false}
{"SimulationId":1,"DeathTime":96.3818359375,"BehaviourName":"ImplementedBehaviours+Evacuate","ActionName":"EvacuationActions+RunAway","Floor":0,"InRoom":false}
{"SimulationId":1,"DeathTime":99.3818359375,"BehaviourName":"ImplementedBehaviours+Evacuate","ActionName":"EvacuationActions+RunToExit","Floor":0,"InRoom":false}
{"SimulationId":1,"DeathTime":99.3818359375,"BehaviourName":"ImplementedBehaviours+Evacuate","ActionName":"EvacuationActions+RunAway","Floor":0,"InRoom":false}
{"SimulationId":1,"DeathTime":102.3818359375,"BehaviourName":"ImplementedBehaviours+Evacuate","ActionName":"EvacuationActions+RunAway","Floor":0,"InRoom":false}
{"SimulationId":1,"DeathTime":105.3818359375,"BehaviourName":"ImplementedBehaviours+Fight","ActionName":"FightActions+Fight","Floor":1,"InRoom":false}
{"SimulationId":1,"DeathTime":201.3818359375,"BehaviourName":"ImplementedBehaviours+Evacuate","ActionName":"EvacuationActions+RunAway","Floor":0,"InRoom":false}
{"SimulationId":1,"DeathTime":267.3818359375,"BehaviourName":"ImplementedBehaviours+Evacuate","ActionName":"EvacuationActions+RunAway","Floor":1,"InRoom":true}
{"SimulationId":1,"DeathTime":297.3818359375,"BehaviourName":"ImplementedBehaviours+Evacuate","ActionName":"EvacuationActions+RunToExit","Floor":1,"InRoom":false}
{"SimulationId":1,"DeathTime":501.3818359375,"BehaviourName":"ImplementedBehaviours+Fight","ActionName":"FightActions+Fight","Floor":3,"InRoom":true}
{"SimulationId":2,"DeathTime":33.0,"BehaviourName":"ImplementedBehaviours+Fight","ActionName":"FightActions+Fight","Floor":0,"InRoom":true}
{"SimulationId":2,"DeathTime":57.0,"BehaviourName":"ImplementedBehaviours+Fight","ActionName":"FightActions+Fight","Floor":0,"InRoom":false}
{"SimulationId":2,"DeathTime":60.0,"BehaviourName":"ImplementedBehaviours+Evacuate","ActionName":"EvacuationActions+RunAway","Floor":0,"InRoom":false}
{"SimulationId":2,"DeathTime":69.0,"BehaviourName":"ImplementedBehaviours+Fight","ActionName":"FightActions+Fight","Floor":0,"InRoom":false}
{"SimulationId":2,"DeathTime":78.0,"BehaviourName":"ImplementedBehaviours+Fight","ActionName":"FightActions+Fight","Floor":0,"InRoom":false}
{"SimulationId":2,"DeathTime":78.0,"BehaviourName":"ImplementedBehaviours+Fight","ActionName":"FightActions+Fight","Floor":0,"InRoom":false}
{"SimulationId":2,"DeathTime":81.0,"BehaviourName":"ImplementedBehaviours+Evacuate","ActionName":"EvacuationActions+RunAway","Floor":0,"InRoom":false}
{"SimulationId":2,"DeathTime":81.0,"BehaviourName":"ImplementedBehaviours+Fight","ActionName":"FightActions+Fight","Floor":0,"InRoom":false}
{"SimulationId":2,"DeathTime":84.0,"BehaviourName":"ImplementedBehaviours+Fight","ActionName":"FightActions+Fight","Floor":0,"InRoom":false}
{"SimulationId":2,"DeathTime":84.0,"BehaviourName":"ImplementedBehaviours+Evacuate","ActionName":"EvacuationActions+RunToMyRoom","Floor":0,"InRoom":false}
{"SimulationId":2,"DeathTime":90.0,"BehaviourName":"ImplementedBehaviours+Fight","ActionName":"FightActions+Fight","Floor":0,"InRoom":false}
{"SimulationId":2,"DeathTime":90.0,"BehaviourName":"ImplementedBehaviours+Fight","ActionName":"FightActions+Fight","Floor":0,"InRoom":false}
{"SimulationId":2,"DeathTime":93.0,"BehaviourName":"ImplementedBehaviours+Evacuate","ActionName":"EvacuationActions+RunAway","Floor":0,"InRoom":false}
{"SimulationId":2,"DeathTime":102.0,"BehaviourName":"ImplementedBehaviours+Fight","ActionName":"FightActions+Fight","Floor":0,"InRoom":false}
{"SimulationId":2,"DeathTime":108.0,"BehaviourName":"ImplementedBehaviours+Fight","ActionName":"FightActions+Fight","Floor":0,"InRoom":false}
{"SimulationId":2,"DeathTime":114.0,"BehaviourName":"ImplementedBehaviours+Fight","ActionName":"FightActions+Fight","Floor":0,"InRoom":false}
{"SimulationId":2,"DeathTime":120.0,"BehaviourName":"ImplementedBehaviours+Fight","ActionName":"FightActions+Fight","Floor":0,"InRoom":false}
{"SimulationId":2,"DeathTime":126.0,"BehaviourName":"ImplementedBehaviours+Fight","ActionName":"FightActions+Fight","Floor":0,"InRoom":false}
{"SimulationId":2,"DeathTime":126.0,"BehaviourName":"ImplementedBehaviours+Evacuate","ActionName":"EvacuationActions+RunAway","Floor":0,"InRoom":false}
{"SimulationId":2,"DeathTime":126.0,"BehaviourName":"ImplementedBehaviours+Fight","ActionName":"FightActions+Fight","Floor":0,"InRoom":false}
{"SimulationId":2,"DeathTime":129.0,"BehaviourName":"ImplementedBehaviours+Fight","ActionName":"FightActions+Fight","Floor":0,"InRoom":false}
{"SimulationId":2,"DeathTime":129.0,"BehaviourName":"ImplementedBehaviours+Fight","ActionName":"FightActions+Fight","Floor":0,"InRoom":false}
{"SimulationId":2,"DeathTime":132.0,"BehaviourName":"ImplementedBehaviours+Evacuate","ActionName":"EvacuationActions+RunToMyRoom","Floor":0,"InRoom":false}
{"SimulationId":2,"DeathTime":132.0,"BehaviourName":"ImplementedBehaviours+Evacuate","ActionName":"EvacuationActions+RunToMyRoom","Floor":0,"InRoom":false}
{"SimulationId":2,"DeathTime":138.0,"BehaviourName":"ImplementedBehaviours+Evacuate","ActionName":"EvacuationActions+RunAway","Floor":0,"InRoom":false}
{"SimulationId":2,"DeathTime":144.0,"BehaviourName":"ImplementedBehaviours+Evacuate","ActionName":"EvacuationActions+RunAway","Floor":0,"InRoom":false}
{"SimulationId":2,"DeathTime":147.0,"BehaviourName":"ImplementedBehaviours+Fight","ActionName":"FightActions+Fight","Floor":0,"InRoom":false}
{"SimulationId":2,"DeathTime":150.0,"BehaviourName":"ImplementedBehaviours+Evacuate","ActionName":"EvacuationActions+RunAway","Floor":1,"InRoom":false}
{"SimulationId":2,"DeathTime":255.0,"BehaviourName":"ImplementedBehaviours+Fight","ActionName":"FightActions+Fight","Floor":0,"InRoom":true}
{"SimulationId":2,"DeathTime":282.0,"BehaviourName":"ImplementedBehaviours+Evacuate","ActionName":"EvacuationActions+RunToExit","Floor":1,"InRoom":false}
{"SimulationId":2,"DeathTime":369.0,"BehaviourName":"ImplementedBehaviours+Fight","ActionName":"FightActions+Fight","Floor":1,"InRoom":true}
{"SimulationId":2,"DeathTime":540.0,"BehaviourName":"ImplementedBehaviours+Fight","ActionName":"FightActions+Fight","Floor":2,"InRoom":true}
{"SimulationId":2,"DeathTime":558.0,"BehaviourName":"ImplementedBehaviours+Evacuate","ActionName":"EvacuationActions+RunAway","Floor":2,"InRoom":false}
{"SimulationId":2,"DeathTime":561.0,"BehaviourName":"ImplementedBehaviours+Evacuate","ActionName":"EvacuationActions+RunToExit","Floor":2,"InRoom":false}
{"SimulationId":3,"DeathTime":66.0,"BehaviourName":"ImplementedBehaviours+Work","ActionName":"WorkActions+GoToWork","Floor":3,"InRoom":true}
{"SimulationId":3,"DeathTime":96.0,"BehaviourName":"ImplementedBehaviours+Fight","ActionName":"FightActions+Fight","Floor":2,"InRoom":false}
{"SimulationId":3,"DeathTime":96.0,"BehaviourName":"ImplementedBehaviours+Fight","ActionName":"FightActions+Fight","Floor":2,"InRoom":false}
{"SimulationId":3,"DeathTime":99.0,"BehaviourName":"ImplementedBehaviours+Fight","ActionName":"FightActions+Fight","Floor":2,"InRoom":false}
{"SimulationId":3,"DeathTime":102.0,"BehaviourName":"ImplementedBehaviours+Fight","ActionName":"FightActions+Fight","Floor":2,"InRoom":false}
{"SimulationId":3,"DeathTime":105.0,"BehaviourName":"ImplementedBehaviours+Fight","ActionName":"FightActions+Fight","Floor":2,"InRoom":false}
{"SimulationId":3,"DeathTime":105.0,"BehaviourName":"ImplementedBehaviours+Evacuate","ActionName":"EvacuationActions+RunAway","Floor":2,"InRoom":false}
{"SimulationId":3,"DeathTime":105.0,"BehaviourName":"ImplementedBehaviours+Evacuate","ActionName":"EvacuationActions+RunAway","Floor":2,"InRoom":false}
{"SimulationId":3,"DeathTime":111.0,"BehaviourName":"ImplementedBehaviours+Fight","ActionName":"FightActions+Fight","Floor":2,"InRoom":false}
{"SimulationId":3,"DeathTime":111.0,"BehaviourName":"ImplementedBehaviours+Fight","ActionName":"FightActions+Fight","Floor":2,"InRoom":false}
{"SimulationId":3,"DeathTime":111.0,"BehaviourName":"ImplementedBehaviours+Fight","ActionName":"FightActions+Fight","Floor":2,"InRoom":false}
{"SimulationId":3,"DeathTime":111.0,"BehaviourName":"ImplementedBehaviours+Evacuate","ActionName":"EvacuationActions+RunAway","Floor":2,"InRoom":false}
{"SimulationId":3,"DeathTime":114.0,"BehaviourName":"ImplementedBehaviours+Evacuate","ActionName":"EvacuationActions+RunAway","Floor":2,"InRoom":false}
{"SimulationId":3,"DeathTime":117.0,"BehaviourName":"ImplementedBehaviours+Fight","ActionName":"FightActions+Fight","Floor":2,"InRoom":false}
{"SimulationId":3,"DeathTime":123.0,"BehaviourName":"ImplementedBehaviours+Fight","ActionName":"FightActions+Fight","Floor":2,"InRoom":false}
{"SimulationId":4,"DeathTime":33.0,"BehaviourName":"ImplementedBehaviours+Work","ActionName":"WorkActions+GoToWork","Floor":0,"InRoom":true}
{"SimulationId":4,"DeathTime":45.0,"BehaviourName":"ImplementedBehaviours+Evacuate","ActionName":"EvacuationActions+RunAway","Floor":0,"InRoom":true}
{"SimulationId":4,"DeathTime":54.0,"BehaviourName":"ImplementedBehaviours+Evacuate","ActionName":"EvacuationActions+RunAway","Floor":0,"InRoom":false}
{"SimulationId":4,"DeathTime":57.0,"BehaviourName":"ImplementedBehaviours+Fight","ActionName":"FightActions+Fight","Floor":0,"InRoom":false}
{"SimulationId":4,"DeathTime":75.0,"BehaviourName":"ImplementedBehaviours+Evacuate","ActionName":"EvacuationActions+RunAway","Floor":0,"InRoom":false}
{"SimulationId":4,"DeathTime":75.0,"BehaviourName":"ImplementedBehaviours+Evacuate","ActionName":"EvacuationActions+RunAway","Floor":0,"InRoom":false}
{"SimulationId":4,"DeathTime":78.0,"BehaviourName":"ImplementedBehaviours+Evacuate","ActionName":"EvacuationActions+RunAway","Floor":0,"InRoom":false}
{"SimulationId":4,"DeathTime":81.0,"BehaviourName":"ImplementedBehaviours+Fight","ActionName":"FightActions+Fight","Floor":0,"InRoom":false}
{"SimulationId":4,"DeathTime":81.0,"BehaviourName":"ImplementedBehaviours+Fight","ActionName":"FightActions+Fight","Floor":0,"InRoom":false}
{"SimulationId":4,"DeathTime":87.0,"BehaviourName":"ImplementedBehaviours+Fight","ActionName":"FightActions+Fight","Floor":0,"InRoom":false}
{"SimulationId":4,"DeathTime":90.0,"BehaviourName":"ImplementedBehaviours+Fight","ActionName":"FightActions+Fight","Floor":0,"InRoom":false}
{"SimulationId":4,"DeathTime":90.0,"BehaviourName":"ImplementedBehaviours+Evacuate","ActionName":"EvacuationActions+RunAway","Floor":0,"InRoom":false}
{"SimulationId":4,"DeathTime":93.0,"BehaviourName":"ImplementedBehaviours+Evacuate","ActionName":"EvacuationActions+RunToMyRoom","Floor":0,"InRoom":false}
{"SimulationId":4,"DeathTime":93.0,"BehaviourName":"ImplementedBehaviours+Evacuate","ActionName":"EvacuationActions+RunAway","Floor":0,"InRoom":false}
{"SimulationId":4,"DeathTime":93.0,"BehaviourName":"ImplementedBehaviours+Fight","ActionName":"FightActions+Fight","Floor":0,"InRoom":false}
{"SimulationId":4,"DeathTime":93.0,"BehaviourName":"ImplementedBehaviours+Evacuate","ActionName":"EvacuationActions+RunToExit","Floor":0,"InRoom":false}
{"SimulationId":4,"DeathTime":96.0,"BehaviourName":"ImplementedBehaviours+Fight","ActionName":"FightActions+Fight","Floor":0,"InRoom":false}
{"SimulationId":4,"DeathTime":96.0,"BehaviourName":"ImplementedBehaviours+Evacuate","ActionName":"EvacuationActions+RunToExit","Floor":0,"InRoom":false}
{"SimulationId":4,"DeathTime":99.0,"BehaviourName":"ImplementedBehaviours+Fight","ActionName":"FightActions+Fight","Floor":0,"InRoom":false}
{"SimulationId":4,"DeathTime":102.0,"BehaviourName":"ImplementedBehaviours+Evacuate","ActionName":"EvacuationActions+RunToAnyRoom","Floor":0,"InRoom":false}
{"SimulationId":4,"DeathTime":102.0,"BehaviourName":"ImplementedBehaviours+Evacuate","ActionName":"EvacuationActions+RunToAnyRoom","Floor":0,"InRoom":false}
{"SimulationId":4,"DeathTime":102.0,"BehaviourName":"ImplementedBehaviours+Evacuate","ActionName":"EvacuationActions+RunToExit","Floor":0,"InRoom":false}
{"SimulationId":4,"DeathTime":105.0,"BehaviourName":"ImplementedBehaviours+Evacuate","ActionName":"EvacuationActions+RunToExit","Floor":0,"InRoom":false}
{"SimulationId":4,"DeathTime":105.0,"BehaviourName":"ImplementedBehaviours+Fight","ActionName":"FightActions+Fight","Floor":0,"InRoom":false}
{"SimulationId":4,"DeathTime":111.0,"BehaviourName":"ImplementedBehaviours+Fight","ActionName":"FightActions+Fight","Floor":1,"InRoom":false}
{"SimulationId":4,"DeathTime":159.0,"BehaviourName":"ImplementedBehaviours+Fight","ActionName":"FightActions+Fight","Floor":1,"InRoom":true}
{"SimulationId":4,"DeathTime":183.0,"BehaviourName":"ImplementedBehaviours+Evacuate","ActionName":"EvacuationActions+RunAway","Floor":1,"InRoom":false}
{"SimulationId":4,"DeathTime":228.0,"BehaviourName":"ImplementedBehaviours+Fight","ActionName":"FightActions+Fight","Floor":1,"InRoom":false}
{"SimulationId":4,"DeathTime":231.0,"BehaviourName":"ImplementedBehaviours+Fight","ActionName":"FightActions+Fight","Floor":1,"InRoom":false}
{"SimulationId":4,"DeathTime":231.0,"BehaviourName":"ImplementedBehaviours+Evacuate","ActionName":"EvacuationActions+RunToExit","Floor":1,"InRoom":false}
{"SimulationId":4,"DeathTime":234.0,"BehaviourName":"ImplementedBehaviours+Fight","ActionName":"FightActions+Fight","Floor":1,"InRoom":false}
{"SimulationId":4,"DeathTime":339.0,"BehaviourName":"ImplementedBehaviours+Fight","ActionName":"FightActions+Fight","Floor":2,"InRoom":true}
{"SimulationId":4,"DeathTime":639.0,"BehaviourName":"ImplementedBehaviours+Fight","ActionName":"FightActions+Fight","Floor":5,"InRoom":true}
{"SimulationId":4,"DeathTime":867.0,"BehaviourName":"ImplementedBehaviours+Fight","ActionName":"FightActions+Fight","Floor":2,"InRoom":true}
{"SimulationId":5,"DeathTime":33.0,"BehaviourName":"ImplementedBehaviours+Fight","ActionName":"FightActions+Fight","Floor":0,"InRoom":true}
{"SimulationId":5,"DeathTime":45.0,"BehaviourName":"ImplementedBehaviours+Fight","ActionName":"FightActions+Fight","Floor":0,"InRoom":true}
{"SimulationId":5,"DeathTime":57.0,"BehaviourName":"ImplementedBehaviours+Evacuate","ActionName":"EvacuationActions+RunAway","Floor":0,"InRoom":false}
{"SimulationId":5,"DeathTime":60.0,"BehaviourName":"ImplementedBehaviours+Fight","ActionName":"FightActions+Fight","Floor":0,"InRoom":false}
{"SimulationId":5,"DeathTime":72.0,"BehaviourName":"ImplementedBehaviours+Fight","ActionName":"FightActions+Fight","Floor":0,"InRoom":true}
{"SimulationId":5,"DeathTime":81.0,"BehaviourName":"ImplementedBehaviours+Evacuate","ActionName":"EvacuationActions+RunAway","Floor":0,"InRoom":false}
{"SimulationId":5,"DeathTime":84.0,"BehaviourName":"ImplementedBehaviours+Fight","ActionName":"FightActions+Fight","Floor":0,"InRoom":false}
{"SimulationId":5,"DeathTime":87.0,"BehaviourName":"ImplementedBehaviours+Evacuate","ActionName":"EvacuationActions+RunAway","Floor":0,"InRoom":false}
{"SimulationId":5,"DeathTime":87.0,"BehaviourName":"ImplementedBehaviours+Fight","ActionName":"FightActions+Fight","Floor":0,"InRoom":false}
{"SimulationId":5,"DeathTime":87.0,"BehaviourName":"ImplementedBehaviours+Fight","ActionName":"FightActions+Fight","Floor":0,"InRoom":false}
{"SimulationId":5,"DeathTime":90.0,"BehaviourName":"ImplementedBehaviours+Fight","ActionName":"FightActions+Fight","Floor":0,"InRoom":false}
{"SimulationId":5,"DeathTime":93.0,"BehaviourName":"ImplementedBehaviours+Evacuate","ActionName":"EvacuationActions+RunToExit","Floor":0,"InRoom":false}
{"SimulationId":5,"DeathTime":96.0,"BehaviourName":"ImplementedBehaviours+Fight","ActionName":"FightActions+Fight","Floor":0,"InRoom":false}
{"SimulationId":5,"DeathTime":96.0,"BehaviourName":"ImplementedBehaviours+Fight","ActionName":"FightActions+Fight","Floor":0,"InRoom":false}
{"SimulationId":5,"DeathTime":96.0,"BehaviourName":"ImplementedBehaviours+Evacuate","ActionName":"EvacuationActions+RunToExit","Floor":0,"InRoom":false}
{"SimulationId":5,"DeathTime":99.0,"BehaviourName":"ImplementedBehaviours+Fight","ActionName":"FightActions+Fight","Floor":0,"InRoom":false}
{"SimulationId":5,"DeathTime":99.0,"BehaviourName":"ImplementedBehaviours+Fight","ActionName":"FightActions+Fight","Floor":0,"InRoom":false}
{"SimulationId":5,"DeathTime":99.0,"BehaviourName":"ImplementedBehaviours+Fight","ActionName":"FightActions+Fight","Floor":0,"InRoom":false}
{"SimulationId":5,"DeathTime":102.0,"BehaviourName":"ImplementedBehaviours+Fight","ActionName":"FightActions+Fight","Floor":0,"InRoom":false}
{"SimulationId":5,"DeathTime":102.0,"BehaviourName":"ImplementedBehaviours+Evacuate","ActionName":"EvacuationActions+RunAway","Floor":0,"InRoom":false}
{"SimulationId":5,"DeathTime":111.0,"BehaviourName":"ImplementedBehaviours+Fight","ActionName":"FightActions+Fight","Floor":1,"InRoom":false}
{"SimulationId":6,"DeathTime":33.0,"BehaviourName":"ImplementedBehaviours+Evacuate","ActionName":"EvacuationActions+RunAway","Floor":0,"InRoom":true}
{"SimulationId":6,"DeathTime":45.0,"BehaviourName":"ImplementedBehaviours+Fight","ActionName":"FightActions+Fight","Floor":0,"InRoom":true}
{"SimulationId":6,"DeathTime":54.0,"BehaviourName":"ImplementedBehaviours+Fight","ActionName":"FightActions+Fight","Floor":0,"InRoom":false}
{"SimulationId":6,"DeathTime":66.0,"BehaviourName":"ImplementedBehaviours+Fight","ActionName":"FightActions+Fight","Floor":0,"InRoom":true}
{"SimulationId":6,"DeathTime":78.0,"BehaviourName":"ImplementedBehaviours+Fight","ActionName":"FightActions+Fight","Floor":0,"InRoom":false}
{"SimulationId":6,"DeathTime":78.0,"BehaviourName":"ImplementedBehaviours+Fight","ActionName":"FightActions+Fight","Floor":0,"InRoom":false}
{"SimulationId":6,"DeathTime":81.0,"BehaviourName":"ImplementedBehaviours+Evacuate","ActionName":"EvacuationActions+RunAway","Floor":0,"InRoom":false}
{"SimulationId":6,"DeathTime":81.0,"BehaviourName":"ImplementedBehaviours+Evacuate","ActionName":"EvacuationActions+RunAway","Floor":0,"InRoom":false}
{"SimulationId":7,"DeathTime":33.0,"BehaviourName":"ImplementedBehaviours+Fight","ActionName":"FightActions+Fight","Floor":0,"InRoom":true}
{"SimulationId":7,"DeathTime":45.0,"BehaviourName":"ImplementedBehaviours+Evacuate","ActionName":"EvacuationActions+RunAway","Floor":0,"InRoom":true}
{"SimulationId":7,"DeathTime":57.0,"BehaviourName":"ImplementedBehaviours+Fight","ActionName":"FightActions+Fight","Floor":0,"InRoom":false}
{"SimulationId":7,"DeathTime":60.0,"BehaviourName":"ImplementedBehaviours+Fight","ActionName":"FightActions+Fight","Floor":0,"InRoom":false}
{"SimulationId":7,"DeathTime":72.0,"BehaviourName":"ImplementedBehaviours+Fight","ActionName":"FightActions+Fight","Floor":0,"InRoom":false}
{"SimulationId":7,"DeathTime":75.0,"BehaviourName":"ImplementedBehaviours+Fight","ActionName":"FightActions+Fight","Floor":0,"InRoom":false}
{"SimulationId":7,"DeathTime":75.0,"BehaviourName":"ImplementedBehaviours+Fight","ActionName":"FightActions+Fight","Floor":0,"InRoom":false}
{"SimulationId":7,"DeathTime":78.0,"BehaviourName":"ImplementedBehaviours+Evacuate","ActionName":"EvacuationActions+RunToMyRoom","Floor":0,"InRoom":false}
{"SimulationId":7,"DeathTime":81.0,"BehaviourName":"ImplementedBehaviours+Evacuate","ActionName":"EvacuationActions+RunAway","Floor":0,"InRoom":false}
{"SimulationId":7,"DeathTime":81.0,"BehaviourName":"ImplementedBehaviours+Evacuate","ActionName":"EvacuationActions+RunToExit","Floor":0,"InRoom":false}
{"SimulationId":7,"DeathTime":84.0,"BehaviourName":"ImplementedBehaviours+Fight","ActionName":"FightActions+Fight","Floor":0,"InRoom":false}
{"SimulationId":7,"DeathTime":87.0,"BehaviourName":"ImplementedBehaviours+Fight","ActionName":"FightActions+Fight","Floor":0,"InRoom":false}
{"SimulationId":7,"DeathTime":87.0,"BehaviourName":"ImplementedBehaviours+Evacuate","ActionName":"EvacuationActions+RunAway","Floor":0,"InRoom":false}
{"SimulationId":7,"DeathTime":87.0,"BehaviourName":"ImplementedBehaviours+Evacuate","ActionName":"EvacuationActions+RunAway","Floor":0,"InRoom":false}
{"SimulationId":7,"DeathTime":87.0,"BehaviourName":"ImplementedBehaviours+Evacuate","ActionName":"EvacuationActions+RunAway","Floor":0,"InRoom":false}
{"SimulationId":7,"DeathTime":90.0,"BehaviourName":"ImplementedBehaviours+Fight","ActionName":"FightActions+Fight","Floor":0,"InRoom":false}
{"SimulationId":7,"DeathTime":96.0,"BehaviourName":"ImplementedBehaviours+Fight","ActionName":"FightActions+Fight","Floor":0,"InRoom":false}
{"SimulationId":7,"DeathTime":96.0,"BehaviourName":"ImplementedBehaviours+Evacuate","ActionName":"EvacuationActions+RunAway","Floor":0,"InRoom":false}
{"SimulationId":7,"DeathTime":96.0,"BehaviourName":"ImplementedBehaviours+Fight","ActionName":"FightActions+Fight","Floor":0,"InRoom":false}
{"SimulationId":7,"DeathTime":96.0,"BehaviourName":"ImplementedBehaviours+Evacuate","ActionName":"EvacuationActions+RunAway","Floor":0,"InRoom":false}
{"SimulationId":7,"DeathTime":99.0,"BehaviourName":"ImplementedBehaviours+Evacuate","ActionName":"EvacuationActions+RunAway","Floor":0,"InRoom":false}
{"SimulationId":7,"DeathTime":99.0,"BehaviourName":"ImplementedBehaviours+Evacuate","ActionName":"EvacuationActions+RunAway","Floor":0,"InRoom":false}
{"SimulationId":7,"DeathTime":108.0,"BehaviourName":"ImplementedBehaviours+Evacuate","ActionName":"EvacuationActions+RunToExit","Floor":0,"InRoom":false}
{"SimulationId":7,"DeathTime":111.0,"BehaviourName":"ImplementedBehaviours+Evacuate","ActionName":"EvacuationActions+RunAway","Floor":0,"InRoom":false}
{"SimulationId":7,"DeathTime":132.0,"BehaviourName":"ImplementedBehaviours+Fight","ActionName":"FightActions+Fight","Floor":0,"InRoom":true}
{"SimulationId":7,"DeathTime":165.0,"BehaviourName":"ImplementedBehaviours+Evacuate","ActionName":"EvacuationActions+RunAway","Floor":0,"InRoom":false}
{"SimulationId":7,"DeathTime":261.0,"BehaviourName":"ImplementedBehaviours+Fight","ActionName":"FightActions+Fight","Floor":2,"InRoom":true}
{"SimulationId":7,"DeathTime":279.0,"BehaviourName":"ImplementedBehaviours+Fight","ActionName":"FightActions+Fight","Floor":2,"InRoom":true}
{"SimulationId":7,"DeathTime":348.0,"BehaviourName":"ImplementedBehaviours+Fight","ActionName":"FightActions+Fight","Floor":1,"InRoom":true}
{"SimulationId":7,"DeathTime":411.0,"BehaviourName":"ImplementedBehaviours+Fight","ActionName":"FightActions+Fight","Floor":1,"InRoom":false}
{"SimulationId":7,"DeathTime":753.0,"BehaviourName":"ImplementedBehaviours+Evacuate","ActionName":"EvacuationActions+RunAway","Floor":5,"InRoom":true}
{"SimulationId":7,"DeathTime":873.0,"BehaviourName":"ImplementedBehaviours+Evacuate","ActionName":"EvacuationActions+RunAway","Floor":4,"InRoom":true}
{"SimulationId":8,"DeathTime":33.0,"BehaviourName":"ImplementedBehaviours+Fight","ActionName":"FightActions+Fight","Floor":0,"InRoom":true}
{"SimulationId":8,"DeathTime":54.0,"BehaviourName":"ImplementedBehaviours+Fight","ActionName":"FightActions+Fight","Floor":0,"InRoom":false}
{"SimulationId":8,"DeathTime":57.0,"BehaviourName":"ImplementedBehaviours+Fight","ActionName":"FightActions+Fight","Floor":0,"InRoom":false}
{"SimulationId":8,"DeathTime":60.0,"BehaviourName":"ImplementedBehaviours+Evacuate","ActionName":"EvacuationActions+RunAway","Floor":0,"InRoom":false}
{"SimulationId":8,"DeathTime":72.0,"BehaviourName":"ImplementedBehaviours+Fight","ActionName":"FightActions+Fight","Floor":0,"InRoom":false}
{"SimulationId":8,"DeathTime":72.0,"BehaviourName":"ImplementedBehaviours+Fight","ActionName":"FightActions+Fight","Floor":0,"InRoom":false}
{"SimulationId":8,"DeathTime":72.0,"BehaviourName":"ImplementedBehaviours+Evacuate","ActionName":"EvacuationActions+RunAway","Floor":0,"InRoom":false}
{"SimulationId":8,"DeathTime":78.0,"BehaviourName":"ImplementedBehaviours+Fight","ActionName":"FightActions+Fight","Floor":0,"InRoom":false}
{"SimulationId":8,"DeathTime":78.0,"BehaviourName":"ImplementedBehaviours+Evacuate","ActionName":"EvacuationActions+RunAway","Floor":0,"InRoom":false}
{"SimulationId":8,"DeathTime":78.0,"BehaviourName":"ImplementedBehaviours+Fight","ActionName":"FightActions+Fight","Floor":0,"InRoom":false}
{"SimulationId":8,"DeathTime":81.0,"BehaviourName":"ImplementedBehaviours+Fight","ActionName":"FightActions+Fight","Floor":0,"InRoom":false}
{"SimulationId":8,"DeathTime":81.0,"BehaviourName":"ImplementedBehaviours+Evacuate","ActionName":"EvacuationActions+RunAway","Floor":0,"InRoom":false}
{"SimulationId":8,"DeathTime":81.0,"BehaviourName":"ImplementedBehaviours+Fight","ActionName":"FightActions+Fight","Floor":0,"InRoom":false}
{"SimulationId":8,"DeathTime":84.0,"BehaviourName":"ImplementedBehaviours+Fight","ActionName":"FightActions+Fight","Floor":0,"InRoom":false}
{"SimulationId":8,"DeathTime":84.0,"BehaviourName":"ImplementedBehaviours+Fight","ActionName":"FightActions+Fight","Floor":0,"InRoom":false}
{"SimulationId":8,"DeathTime":84.0,"BehaviourName":"ImplementedBehaviours+Evacuate","ActionName":"EvacuationActions+RunAway","Floor":0,"InRoom":false}
{"SimulationId":8,"DeathTime":84.0,"BehaviourName":"ImplementedBehaviours+Fight","ActionName":"FightActions+Fight","Floor":0,"InRoom":false}
{"SimulationId":8,"DeathTime":87.0,"BehaviourName":"ImplementedBehaviours+Fight","ActionName":"FightActions+Fight","Floor":0,"InRoom":false}
{"SimulationId":8,"DeathTime":93.0,"BehaviourName":"ImplementedBehaviours+Evacuate","ActionName":"EvacuationActions+RunAway","Floor":1,"InRoom":false}
{"SimulationId":8,"DeathTime":96.0,"BehaviourName":"ImplementedBehaviours+Evacuate","ActionName":"EvacuationActions+RunToExit","Floor":1,"InRoom":false}
{"SimulationId":8,"DeathTime":99.0,"BehaviourName":"ImplementedBehaviours+Evacuate","ActionName":"EvacuationActions+RunToExit","Floor":1,"InRoom":false}
{"SimulationId":8,"DeathTime":105.0,"BehaviourName":"ImplementedBehaviours+Fight","ActionName":"FightActions+Fight","Floor":2,"InRoom":false}
{"SimulationId":8,"DeathTime":105.0,"BehaviourName":"ImplementedBehaviours+Fight","ActionName":"FightActions+Fight","Floor":2,"InRoom":false}
{"SimulationId":8,"DeathTime":168.0,"BehaviourName":"ImplementedBehaviours+Fight","ActionName":"FightActions+Fight","Floor":3,"InRoom":false}
{"SimulationId":8,"DeathTime":180.0,"BehaviourName":"ImplementedBehaviours+Fight","ActionName":"FightActions+Fight","Floor":3,"InRoom":false}
{"SimulationId":8,"DeathTime":216.0,"BehaviourName":"ImplementedBehaviours+Evacuate","ActionName":"EvacuationActions+RunAway","Floor":3,"InRoom":false}
{"SimulationId":9,"DeathTime":33.0,"BehaviourName":"ImplementedBehaviours+Fight","ActionName":"FightActions+Fight","Floor":0,"InRoom":true}
{"SimulationId":9,"DeathTime":45.0,"BehaviourName":"ImplementedBehaviours+Fight","ActionName":"FightActions+Fight","Floor":0,"InRoom":true}
{"SimulationId":9,"DeathTime":60.0,"BehaviourName":"ImplementedBehaviours+Fight","ActionName":"FightActions+Fight","Floor":0,"InRoom":false}
{"SimulationId":9,"DeathTime":87.0,"BehaviourName":"ImplementedBehaviours+Fight","ActionName":"FightActions+Fight","Floor":0,"InRoom":false}
{"SimulationId":9,"DeathTime":90.0,"BehaviourName":"ImplementedBehaviours+Fight","ActionName":"FightActions+Fight","Floor":0,"InRoom":false}
{"SimulationId":9,"DeathTime":90.0,"BehaviourName":"ImplementedBehaviours+Fight","ActionName":"FightActions+Fight","Floor":0,"InRoom":false}
{"SimulationId":9,"DeathTime":93.0,"BehaviourName":"ImplementedBehaviours+Fight","ActionName":"FightActions+Fight","Floor":0,"InRoom":false}
{"SimulationId":9,"DeathTime":99.0,"BehaviourName":"ImplementedBehaviours+Fight","ActionName":"FightActions+Fight","Floor":0,"InRoom":false}
{"SimulationId":10,"DeathTime":33.0,"BehaviourName":"ImplementedBehaviours+Work","ActionName":"WorkActions+GoToWork","Floor":0,"InRoom":true}
{"SimulationId":10,"DeathTime":45.0,"BehaviourName":"ImplementedBehaviours+Evacuate","ActionName":"EvacuationActions+RunAway","Floor":0,"InRoom":true}
{"SimulationId":10,"DeathTime":54.0,"BehaviourName":"ImplementedBehaviours+Fight","ActionName":"FightActions+Fight","Floor":0,"InRoom":false}
{"SimulationId":10,"DeathTime":60.0,"BehaviourName":"ImplementedBehaviours+Fight","ActionName":"FightActions+Fight","Floor":0,"InRoom":false}
{"SimulationId":10,"DeathTime":72.0,"BehaviourName":"ImplementedBehaviours+Fight","ActionName":"FightActions+Fight","Floor":0,"InRoom":false}
{"SimulationId":10,"DeathTime":72.0,"BehaviourName":"ImplementedBehaviours+Fight","ActionName":"FightActions+Fight","Floor":0,"InRoom":false}
{"SimulationId":10,"DeathTime":75.0,"BehaviourName":"ImplementedBehaviours+Evacuate","ActionName":"EvacuationActions+RunAway","Floor":0,"InRoom":false}
{"SimulationId":10,"DeathTime":75.0,"BehaviourName":"ImplementedBehaviours+Fight","ActionName":"FightActions+Fight","Floor":0,"InRoom":false}
{"SimulationId":10,"DeathTime":78.0,"BehaviourName":"ImplementedBehaviours+Evacuate","ActionName":"EvacuationActions+RunToExit","Floor":0,"InRoom":false}
{"SimulationId":10,"DeathTime":78.0,"BehaviourName":"ImplementedBehaviours+Fight","ActionName":"FightActions+Fight","Floor":0,"InRoom":false}
{"SimulationId":10,"DeathTime":78.0,"BehaviourName":"ImplementedBehaviours+Fight","ActionName":"FightActions+Fight","Floor":0,"InRoom":false}
{"SimulationId":10,"DeathTime":81.0,"BehaviourName":"ImplementedBehaviours+Evacuate","ActionName":"EvacuationActions+RunToMyRoom","Floor":0,"InRoom":false}
{"SimulationId":10,"DeathTime":84.0,"BehaviourName":"ImplementedBehaviours+Evacuate","ActionName":"EvacuationActions+RunToExit","Floor":0,"InRoom":false}
{"SimulationId":10,"DeathTime":84.0,"BehaviourName":"ImplementedBehaviours+Evacuate","ActionName":"EvacuationActions+RunToExit","Floor":0,"InRoom":false}
{"SimulationId":10,"DeathTime":84.0,"BehaviourName":"ImplementedBehaviours+Evacuate","ActionName":"EvacuationActions+RunToExit","Floor":0,"InRoom":false}
{"SimulationId":10,"DeathTime":96.0,"BehaviourName":"ImplementedBehaviours+Fight","ActionName":"FightActions+Fight","Floor":1,"InRoom":false}
{"SimulationId":10,"DeathTime":96.0,"BehaviourName":"ImplementedBehaviours+Evacuate","ActionName":"EvacuationActions+RunToExit","Floor":1,"InRoom":false}
{"SimulationId":10,"DeathTime":99.0,"BehaviourName":"ImplementedBehaviours+Evacuate","ActionName":"EvacuationActions+RunToExit","Floor":1,"InRoom":false}
{"SimulationId":10,"DeathTime":99.0,"BehaviourName":"ImplementedBehaviours+Fight","ActionName":"FightActions+Fight","Floor":1,"InRoom":false}
{"SimulationId":10,"DeathTime":105.0,"BehaviourName":"ImplementedBehaviours+Fight","ActionName":"FightActions+Fight","Floor":1,"InRoom":false}
{"SimulationId":10,"DeathTime":105.0,"BehaviourName":"ImplementedBehaviours+Evacuate","ActionName":"EvacuationActions+RunToExit","Floor":1,"InRoom":false}
{"SimulationId":10,"DeathTime":108.0,"BehaviourName":"ImplementedBehaviours+Evacuate","ActionName":"EvacuationActions+RunToExit","Floor":1,"InRoom":false}
{"SimulationId":10,"DeathTime":108.0,"BehaviourName":"ImplementedBehaviours+Evacuate","ActionName":"EvacuationActions+RunToExit","Floor":1,"InRoom":false}
{"SimulationId":10,"DeathTime":114.0,"BehaviourName":"ImplementedBehaviours+Evacuate","ActionName":"EvacuationActions+RunToExit","Floor":1,"InRoom":false}
{"SimulationId":10,"DeathTime":114.0,"BehaviourName":"ImplementedBehaviours+Fight","ActionName":"FightActions+Fight","Floor":1,"InRoom":false}
{"SimulationId":10,"DeathTime":114.0,"BehaviourName":"ImplementedBehaviours+Fight","ActionName":"FightActions+Fight","Floor":1,"InRoom":false}
{"SimulationId":10,"DeathTime":117.0,"BehaviourName":"ImplementedBehaviours+Evacuate","ActionName":"EvacuationActions+RunToExit","Floor":1,"InRoom":false}
{"SimulationId":10,"DeathTime":174.0,"BehaviourName":"ImplementedBehaviours+Evacuate","ActionName":"EvacuationActions+RunAway","Floor":1,"InRoom":false}
{"SimulationId":10,"DeathTime":183.0,"BehaviourName":"ImplementedBehaviours+Fight","ActionName":"FightActions+Fight","Floor":1,"InRoom":false}
{"SimulationId":10,"DeathTime":183.0,"BehaviourName":"ImplementedBehaviours+Fight","ActionName":"FightActions+Fight","Floor":1,"InRoom":false}
